deksecrets-0.1.31.dist-info/METADATA
deksecrets-0.1.31.dist-info/WHEEL
deksecrets-0.1.31.dist-info/entry_points.txt
deksecrets/click/__entry__.py
deksecrets/click/__init__.py
deksecrets/click/gitea.py
deksecrets/click/infisical.py
deksecrets/click/k8s.py
deksecrets/core/__init__.py
deksecrets/core/gitea.py
deksecrets/core/infisical.py
deksecrets/tools/__init__.py
deksecrets/tools/gitea.py
deksecrets-0.1.31.dist-info/RECORD
