Metadata-Version: 2.1
Name: deksecrets
Version: 0.1.31
Author-Email: sanzenwin <sanzenwin@gmail.com>
License: MIT
Requires-Python: >=3.10
Requires-Dist: py-gitea<=0.2.8
Requires-Dist: infisical-python<=2.1.8
Requires-Dist: dektools[yaml]<1.0.0
